repyle/__init__.py
repyle/py.typed
repyle-0.0.0.dist-info/LICENSE
repyle-0.0.0.dist-info/WHEEL
repyle-0.0.0.dist-info/METADATA
repyle-0.0.0.dist-info/RECORD
