Metadata-Version: 2.1
Name: repyle
Version: 0.0.0
Summary: Python Hot Reloading
License: GPL-3.0-only
Author: Markus Feiks
Author-email: github@feyx.de
Requires-Python: >=3.10,<4.0
Classifier: License :: OSI Approved :: GNU General Public License v3 (GPLv3)
Classifier: Programming Language :: Python :: 3
Classifier: Programming Language :: Python :: 3.10
